distributed/__init__.py
distributed/_async_taskgroup.py
distributed/_asyncio.py
distributed/_concurrent_futures_thread.py
distributed/_signals.py
distributed/_stories.py
distributed/_version.py
distributed/active_memory_manager.py
distributed/actor.py
distributed/batched.py
distributed/bokeh.py
distributed/broker.py
distributed/cfexecutor.py
distributed/chaos.py
distributed/client.py
distributed/cluster_dump.py
distributed/collections.py
distributed/compatibility.py
distributed/config.py
distributed/core.py
distributed/counter.py
distributed/diskutils.py
distributed/distributed-schema.yaml
distributed/distributed.yaml
distributed/event.py
distributed/exceptions.py
distributed/gc.py
distributed/itertools.py
distributed/lock.py
distributed/metrics.py
distributed/multi_lock.py
distributed/nanny.py
distributed/node.py
distributed/objects.py
distributed/preloading.py
distributed/process.py
distributed/proctitle.py
distributed/profile.py
distributed/publish.py
distributed/py.typed
distributed/queues.py
distributed/recreate_tasks.py
distributed/scheduler.py
distributed/security.py
distributed/semaphore.py
distributed/sizeof.py
distributed/spans.py
distributed/spill.py
distributed/stealing.py
distributed/system.py
distributed/system_monitor.py
distributed/threadpoolexecutor.py
distributed/utils.py
distributed/utils_comm.py
distributed/utils_test.py
distributed/variable.py
distributed/versions.py
distributed/worker.py
distributed/worker_client.py
distributed/worker_memory.py
distributed/worker_state_machine.py
distributed/cli/__init__.py
distributed/cli/dask_scheduler.py
distributed/cli/dask_spec.py
distributed/cli/dask_ssh.py
distributed/cli/dask_worker.py
distributed/cli/utils.py
distributed/comm/__init__.py
distributed/comm/addressing.py
distributed/comm/core.py
distributed/comm/inproc.py
distributed/comm/registry.py
distributed/comm/tcp.py
distributed/comm/ucx.py
distributed/comm/utils.py
distributed/comm/ws.py
distributed/dashboard/__init__.py
distributed-2025.12.0.dist-info/licenses/LICENSE.txt
distributed-2025.12.0.dist-info/METADATA
distributed-2025.12.0.dist-info/WHEEL
distributed-2025.12.0.dist-info/entry_points.txt
distributed-2025.12.0.dist-info/top_level.txt
distributed-2025.12.0.dist-info/RECORD
