Metadata-Version: 2.4
Name: distributed
Version: 2025.12.0
Summary: Distributed scheduler for Dask
Maintainer-email: Matthew Rocklin <mrocklin@gmail.com>
License-Expression: BSD-3-Clause
Project-URL: Homepage, https://distributed.dask.org
Project-URL: Source, https://github.com/dask/distributed
Classifier: Development Status :: 5 - Production/Stable
Classifier: Intended Audience :: Developers
Classifier: Intended Audience :: Science/Research
Classifier: Operating System :: OS Independent
Classifier: Programming Language :: Python
Classifier: Programming Language :: Python :: 3
Classifier: Programming Language :: Python :: 3 :: Only
Classifier: Programming Language :: Python :: 3.10
Classifier: Programming Language :: Python :: 3.11
Classifier: Programming Language :: Python :: 3.12
Classifier: Programming Language :: Python :: 3.13
Classifier: Topic :: Scientific/Engineering
Classifier: Topic :: System :: Distributed Computing
Requires-Python: >=3.10
License-File: LICENSE.txt
Requires-Dist: click>=8.0
Requires-Dist: cloudpickle>=3.0.0
Requires-Dist: dask<2025.12.1,>=2025.12.0
Requires-Dist: jinja2>=2.10.3
Requires-Dist: locket>=1.0.0
Requires-Dist: msgpack>=1.0.2
Requires-Dist: packaging>=20.0
Requires-Dist: psutil>=5.8.0
Requires-Dist: pyyaml>=5.4.1
Requires-Dist: sortedcontainers>=2.0.5
Requires-Dist: tblib!=3.2.0,!=3.2.1,>=1.6.0
Requires-Dist: toolz>=0.12.0
Requires-Dist: tornado>=6.2.0
Requires-Dist: urllib3>=1.26.5
Requires-Dist: zict>=3.0.0
Dynamic: license-file
